{
  "listings": {
    "realtor_5509849733": {
      "address": "1280 Oxford Rd Bridgewater Twp NJ 08807",
      "price": 749999,
      "beds": 3,
      "baths": "2",
      "lot_sqft": 32234,
      "url": "https://www.realtor.com/realestateandhomes-detail/1280-Oxford-Rd_Bridgewater_NJ_08807_M55098-49733",
      "status": "think",
      "first_seen": "2026-07-15",
      "source": "Realtor.com",
      "christine_favorite": false,
      "christine_pass": false
    },
    "realtor_5736063451": {
      "address": "653 Foothill Rd Bridgewater Twp NJ 08807",
      "price": 675000,
      "beds": 3,
      "baths": "2.5",
      "lot_sqft": 37026,
      "url": "https://www.realtor.com/realestateandhomes-detail/653-Foothill-Rd_Bridgewater_NJ_08807_M57360-63451",
      "status": "favorite",
      "first_seen": "2026-07-15",
      "source": "Realtor.com"
    },
    "realtor_5716817257": {
      "address": "1813 Washington Valley Rd Bridgewater Twp NJ 08836",
      "price": 595000,
      "beds": 3,
      "baths": "2",
      "lot_sqft": 196020,
      "url": "https://www.realtor.com/realestateandhomes-detail/1813-Washington-Valley-Rd_Martinsville_NJ_08836_M57168-17257",
      "status": "new",
      "first_seen": "2026-07-15",
      "source": "Realtor.com"
    },
    "realtor_6811292095": {
      "address": "487 Knollwood Dr Bridgewater Twp NJ 08807",
      "price": 768880,
      "beds": 3,
      "baths": "2",
      "lot_sqft": 47916,
      "url": "https://www.realtor.com/realestateandhomes-detail/487-Knollwood-Dr_Bridgewater_NJ_08807_M68112-92095",
      "status": "new",
      "first_seen": "2026-07-15",
      "source": "Realtor.com"
    },
    "realtor_5534426697": {
      "address": "36 Leghorn Ave Bridgewater Twp NJ 08807",
      "price": 600000,
      "beds": 3,
      "baths": "2",
      "lot_sqft": 11761,
      "url": "https://www.realtor.com/realestateandhomes-detail/36-Leghorn-Ave_Bridgewater_NJ_08807_M55344-26697",
      "status": "think",
      "first_seen": "2026-07-15",
      "source": "Realtor.com"
    },
    "realtor_9403175827": {
      "address": "1105 Route202206 Bridgewater Twp NJ 08807",
      "price": 524700,
      "beds": 3,
      "baths": "2",
      "lot_sqft": 18295,
      "url": "https://www.realtor.com/realestateandhomes-detail/1105-Route202206_Bridgewater-Twp_NJ_08807_M94031-75827",
      "status": "new",
      "first_seen": "2026-07-15",
      "source": "Realtor.com"
    },
    "redfin_37788553": {
      "address": "1352 Crim Rd Bridgewater NJ 08807",
      "price": 749000,
      "beds": 4,
      "baths": 3,
      "lot_sqft": null,
      "url": "https://www.redfin.com/NJ/Bridgewater/1352-Crim-Rd-08807/home/37788553",
      "status": "new",
      "first_seen": "2026-07-15",
      "source": "Redfin"
    },
    "zillow_39912765": {
      "address": "44 Second St Somerville Boro NJ 08876",
      "price": 500000,
      "beds": 5,
      "baths": 2,
      "lot_sqft": "5,227 sqft",
      "url": "https://www.zillow.com/homedetails/39912765_zpid/",
      "status": "new",
      "first_seen": "2026-07-15",
      "source": "Zillow"
    },
    "redfin_36855599": {
      "id": "redfin_36855599",
      "address": "1520 Evelyn Ave North Brunswick NJ 08902",
      "price": "595000",
      "beds": 3,
      "baths": 2,
      "lot_sqft": null,
      "url": "https://www.redfin.com/NJ/North-Brunswick/1520-Evelyn-Ave-08902/home/36855599",
      "source": "Redfin",
      "basement_label": "✅ Basement",
      "garage_label": "🚗 Unknown",
      "property_road": "🏘️ Residential Street (Evelyn Avenue)",
      "busy_road": true,
      "near_highway": true,
      "highway_roads": [
        {
          "name": "Lincoln Highway",
          "distance_miles": 0.07
        }
      ],
      "status": "new",
      "first_seen": "2026-07-16"
    },
    "redfin_36855306": {
      "id": "redfin_36855306",
      "address": "4 Taylor Dr New Brunswick NJ 08901",
      "price": "599900",
      "beds": 4,
      "baths": 2.5,
      "lot_sqft": "11270",
      "url": "https://www.redfin.com/NJ/New-Brunswick/4-Taylor-Dr-08901/home/36855306",
      "source": "Redfin",
      "basement_label": "✅ Basement",
      "garage_label": "🚗 Unknown",
      "property_road": "🏘️ Residential Street (Taylor Drive)",
      "busy_road": false,
      "near_highway": false,
      "highway_roads": [],
      "status": "new",
      "first_seen": "2026-07-16"
    },
    "redfin_36834681": {
      "id": "redfin_36834681",
      "address": "5 Pardun St Milltown NJ 08850",
      "price": "775000",
      "beds": 3,
      "baths": 2.5,
      "lot_sqft": "18901",
      "url": "https://www.redfin.com/NJ/Milltown/5-Pardun-Ave-08850/home/36834681",
      "source": "Redfin",
      "basement_label": "✅ Basement",
      "garage_label": "🚗 Unknown",
      "property_road": "🏘️ Residential Street (Pardun Avenue)",
      "busy_road": false,
      "near_highway": false,
      "highway_roads": [],
      "status": "new",
      "first_seen": "2026-07-16"
    },
    "redfin_36574972": {
      "id": "redfin_36574972",
      "address": "7 Smith Branch Rd Whitehouse Station NJ 08889",
      "price": "750000",
      "beds": 3,
      "baths": 2,
      "lot_sqft": "84942",
      "url": "https://www.redfin.com/NJ/Whitehouse-Station/7-Smith-Branch-Rd-08889/home/36574972",
      "source": "Redfin",
      "basement_label": "✅ Basement",
      "garage_label": "🚗 Unknown",
      "property_road": "🏘️ Residential Street (Smith Branch Road)",
      "busy_road": false,
      "near_highway": false,
      "highway_roads": [],
      "status": "new",
      "first_seen": "2026-07-16"
    },
    "redfin_37737826": {
      "id": "redfin_37737826",
      "address": "115 Fairview Dr Branchburg NJ 08853",
      "price": "840000",
      "beds": 4,
      "baths": 2,
      "lot_sqft": "95745",
      "url": "https://www.redfin.com/NJ/Branchburg/115-Fairview-Dr-08853/home/37737826",
      "source": "Redfin",
      "basement_label": "✅ Basement",
      "garage_label": "🚗 Unknown",
      "property_road": "🏘️ Residential Street (Fairview Drive)",
      "busy_road": false,
      "near_highway": false,
      "highway_roads": [],
      "status": "new",
      "first_seen": "2026-07-16"
    },
    "redfin_36984627": {
      "id": "redfin_36984627",
      "address": "310 Pitt St South Plainfield NJ 07080",
      "price": "575000",
      "beds": 4,
      "baths": 3,
      "lot_sqft": null,
      "url": "https://www.redfin.com/NJ/South-Plainfield/310-Pitt-St-07080/home/36984627",
      "source": "Redfin",
      "basement_label": "✅ Basement",
      "garage_label": "🚗 Unknown",
      "property_road": "🏘️ Residential Street (Pitt Street)",
      "busy_road": false,
      "near_highway": false,
      "highway_roads": [],
      "status": "new",
      "first_seen": "2026-07-16"
    },
    "redfin_37859678": {
      "id": "redfin_37859678",
      "address": "33 Ellison Rd Somerset NJ 08873",
      "price": "599900",
      "beds": 3,
      "baths": 2,
      "lot_sqft": "57064",
      "url": "https://www.redfin.com/NJ/Somerset/33-Ellison-Rd-08873/home/37859678",
      "source": "Redfin",
      "basement_label": "✅ Basement",
      "garage_label": "🚗 Unknown",
      "property_road": "🏘️ Residential Street (Ellison Road)",
      "busy_road": false,
      "near_highway": false,
      "highway_roads": [],
      "status": "new",
      "first_seen": "2026-07-16"
    },
    "redfin_36829986": {
      "id": "redfin_36829986",
      "address": "154 Mulberry Ln Middlesex NJ 08846",
      "price": "645000",
      "beds": 3,
      "baths": 2,
      "lot_sqft": "9749",
      "url": "https://www.redfin.com/NJ/Middlesex/154-Mulberry-Ln-08846/home/36829986",
      "source": "Redfin",
      "basement_label": "✅ Basement",
      "garage_label": "🚗 Unknown",
      "property_road": "🏘️ Residential Street (Mulberry Lane)",
      "busy_road": true,
      "near_highway": true,
      "highway_roads": [
        {
          "name": "557-541 NJ-28",
          "distance_miles": 0.18
        }
      ],
      "status": "new",
      "first_seen": "2026-07-16"
    },
    "redfin_37034616": {
      "id": "redfin_37034616",
      "address": "200 Cedar Ave Highland Park NJ 08904",
      "price": "589000",
      "beds": 5,
      "baths": 3,
      "lot_sqft": "9993",
      "url": "https://www.redfin.com/NJ/Highland-Park/200-Cedar-Ave-08904/home/37034616",
      "source": "Redfin",
      "basement_label": "✅ Basement",
      "garage_label": "🚗 Unknown",
      "property_road": "🏘️ Residential Street (Cedar Avenue)",
      "busy_road": false,
      "near_highway": false,
      "highway_roads": [],
      "status": "new",
      "first_seen": "2026-07-16"
    },
    "redfin_201570654": {
      "id": "redfin_201570654",
      "address": "544 W 8th St W Plainfield NJ 07060",
      "price": "875000",
      "beds": 5,
      "baths": 4,
      "lot_sqft": "57499",
      "url": "https://www.redfin.com/NJ/Plainfield/544-W-8th-St-07060/home/201570654",
      "source": "Redfin",
      "basement_label": "✅ Basement",
      "garage_label": "🚗 Unknown",
      "property_road": "🏘️ Residential Street (West 8th Street)",
      "busy_road": true,
      "near_highway": true,
      "highway_roads": [
        {
          "name": "417-351 NJ-28",
          "distance_miles": 0.26
        }
      ],
      "status": "new",
      "first_seen": "2026-07-16"
    },
    "redfin_36981591": {
      "id": "redfin_36981591",
      "address": "929 Franklin Ave South Plainfield NJ 07080",
      "price": "789000",
      "beds": 4,
      "baths": 2.5,
      "lot_sqft": null,
      "url": "https://www.redfin.com/NJ/South-Plainfield/929-Franklin-Ave-07080/home/36981591",
      "source": "Redfin",
      "basement_label": "✅ Basement",
      "garage_label": "🚗 Unknown",
      "property_road": "🏘️ Residential Street (Franklin Avenue)",
      "busy_road": false,
      "near_highway": false,
      "highway_roads": [],
      "status": "new",
      "first_seen": "2026-07-16"
    },
    "redfin_36915767": {
      "id": "redfin_36915767",
      "address": "247 Adams St Piscataway NJ 08854",
      "price": "649999",
      "beds": 5,
      "baths": 4,
      "lot_sqft": "9078",
      "url": "https://www.redfin.com/NJ/Piscataway/247-Adams-St-08854/home/36915767",
      "source": "Redfin",
      "basement_label": "✅ Basement",
      "garage_label": "🚗 Unknown",
      "property_road": "🏘️ Residential Street (Adams Street)",
      "busy_road": false,
      "near_highway": false,
      "highway_roads": [],
      "status": "new",
      "first_seen": "2026-07-16"
    },
    "zillow_39864819": {
      "id": "zillow_39864819",
      "address": "1352 Crim Road Bridgewater Twp. NJ 08807",
      "price": 749000,
      "beds": 4,
      "baths": 4,
      "lot_sqft": "2.07 acres",
      "url": "https://www.zillow.com/homedetails/39864819_zpid/",
      "source": "Zillow",
      "busy_road": false,
      "near_highway": false,
      "near_industrial": true,
      "status": "new",
      "first_seen": "2026-07-16"
    },
    "zillow_39864242": {
      "id": "zillow_39864242",
      "address": "1280 Oxford Rd Bridgewater Twp. NJ 08807",
      "price": 749999,
      "beds": 3,
      "baths": 2,
      "lot_sqft": "0.74 acres",
      "url": "https://www.zillow.com/homedetails/39864242_zpid/",
      "source": "Zillow",
      "basement_label": "✅ Unfinished Basement",
      "garage_label": "🚗 2-car attached garage",
      "property_road": "🏘️ Residential Street (Oxford Road)",
      "busy_road": false,
      "near_highway": false,
      "highway_roads": [],
      "status": "new",
      "first_seen": "2026-07-16"
    },
    "zillow_39864179": {
      "id": "zillow_39864179",
      "address": "792 Partridge Dr Bridgewater Twp. NJ 08807",
      "price": {
        "value": 1500000
      },
      "beds": 4,
      "baths": 3,
      "lot_sqft": "1.03 acres",
      "url": "https://www.zillow.com/homedetails/39864179_zpid/",
      "source": "Zillow",
      "busy_road": false,
      "near_highway": false,
      "near_industrial": true,
      "status": "new",
      "first_seen": "2026-07-16"
    },
    "zillow_53727000": {
      "id": "zillow_53727000",
      "address": "15 Campbell Ct Bridgewater Twp. NJ 08807",
      "price": {
        "value": 1149000,
        "pricePerSquareFoot": 367
      },
      "beds": 5,
      "baths": 4,
      "lot_sqft": "0.62 acres",
      "url": "https://www.zillow.com/homedetails/53727000_zpid/",
      "source": "Zillow",
      "busy_road": false,
      "near_highway": true,
      "near_industrial": true,
      "status": "new",
      "first_seen": "2026-07-16"
    },
    "zillow_39862639": {
      "id": "zillow_39862639",
      "address": "619 Foothill Rd Bridgewater Twp. NJ 08807",
      "price": {
        "value": 1490000
      },
      "beds": 3,
      "baths": 2,
      "lot_sqft": "4.0 acres",
      "url": "https://www.zillow.com/homedetails/39862639_zpid/",
      "source": "Zillow",
      "busy_road": false,
      "near_highway": false,
      "near_industrial": true,
      "status": "new",
      "first_seen": "2026-07-16"
    },
    "redfin_37013764": {
      "id": "redfin_37013764",
      "address": "27 Fagan Pl Colonia NJ 07067",
      "price": "650000",
      "beds": 3,
      "baths": 2,
      "lot_sqft": "17999",
      "url": "https://www.redfin.com/NJ/Colonia/27-Fagan-Pl-07067/home/37013764",
      "source": "Redfin",
      "basement_label": "✅ Basement",
      "garage_label": "🚗 Unknown",
      "property_road": "🏘️ Residential Street (Fagan Place)",
      "busy_road": true,
      "near_highway": true,
      "highway_roads": [
        {
          "name": "Garden State Parkway",
          "distance_miles": 0.24
        }
      ],
      "status": "new",
      "first_seen": "2026-07-16"
    },
    "redfin_36993833": {
      "id": "redfin_36993833",
      "address": "71 Pine St Spotswood NJ 08884",
      "price": "620000",
      "beds": 3,
      "baths": 2,
      "lot_sqft": null,
      "url": "https://www.redfin.com/NJ/Spotswood/71-Pine-St-08884/home/36993833",
      "source": "Redfin",
      "basement_label": "✅ Basement",
      "garage_label": "🚗 Unknown",
      "property_road": "🏘️ Residential Street (Pine Street)",
      "busy_road": false,
      "near_highway": false,
      "highway_roads": [],
      "status": "new",
      "first_seen": "2026-07-16"
    },
    "redfin_36847993": {
      "id": "redfin_36847993",
      "address": "39 Mcfadden Dr Monroe Township NJ 08831",
      "price": "649000",
      "beds": 3,
      "baths": 2.5,
      "lot_sqft": "13199",
      "url": "https://www.redfin.com/NJ/Monroe-Township/39-McFadden-Dr-08831/home/36847993",
      "source": "Redfin",
      "basement_label": "✅ Basement",
      "garage_label": "🚗 Unknown",
      "property_road": "🏘️ Residential Street (McFadden Drive)",
      "busy_road": false,
      "near_highway": false,
      "highway_roads": [],
      "status": "new",
      "first_seen": "2026-07-16"
    },
    "redfin_36996236": {
      "id": "redfin_36996236",
      "address": "31 Woodview Ave Fords NJ 08863",
      "price": "509900",
      "beds": 3,
      "baths": 2,
      "lot_sqft": "4199",
      "url": "https://www.redfin.com/NJ/Fords/31-Woodview-Ave-08863/home/36996236",
      "source": "Redfin",
      "basement_label": "✅ Basement",
      "garage_label": "🚗 Unknown",
      "property_road": "🏘️ Residential Street (Woodview Avenue)",
      "busy_road": false,
      "near_highway": false,
      "highway_roads": [],
      "status": "new",
      "first_seen": "2026-07-16"
    },
    "redfin_36991236": {
      "id": "redfin_36991236",
      "address": "125 Snowhill St Spotswood NJ 08884",
      "price": "350000",
      "beds": 3,
      "baths": 2,
      "lot_sqft": "8250",
      "url": "https://www.redfin.com/NJ/Spotswood/125-Snowhill-St-08884/home/36991236",
      "source": "Redfin",
      "basement_label": "✅ Basement",
      "garage_label": "🚗 Unknown",
      "property_road": "🟠 Secondary Road (Snowhill Street)",
      "busy_road": false,
      "near_highway": false,
      "highway_roads": [],
      "status": "new",
      "first_seen": "2026-07-16"
    },
    "redfin_36789454": {
      "id": "redfin_36789454",
      "address": "61 Rose St Edison NJ 08817",
      "price": "625000",
      "beds": 3,
      "baths": 2,
      "lot_sqft": "6351",
      "url": "https://www.redfin.com/NJ/Edison/61-Rose-St-08817/home/36789454",
      "source": "Redfin",
      "basement_label": "✅ Basement",
      "garage_label": "🚗 Unknown",
      "property_road": "🏘️ Residential Street (Rose Street)",
      "busy_road": false,
      "near_highway": false,
      "highway_roads": [],
      "status": "new",
      "first_seen": "2026-07-16"
    },
    "redfin_36991997": {
      "id": "redfin_36991997",
      "address": "77 Michael Rd Spotswood NJ 08884",
      "price": "675000",
      "beds": 4,
      "baths": 2.5,
      "lot_sqft": null,
      "url": "https://www.redfin.com/NJ/Spotswood/77-Michael-Rd-08884/home/36991997",
      "source": "Redfin",
      "basement_label": "✅ Basement",
      "garage_label": "🚗 Unknown",
      "property_road": "🏘️ Residential Street (Michael Road)",
      "busy_road": false,
      "near_highway": false,
      "highway_roads": [],
      "status": "new",
      "first_seen": "2026-07-16"
    },
    "redfin_37008427": {
      "id": "redfin_37008427",
      "address": "496 Outlook Ave Colonia NJ 07067",
      "price": "619900",
      "beds": 3,
      "baths": 2,
      "lot_sqft": "9374",
      "url": "https://www.redfin.com/NJ/Colonia/496-Outlook-Ave-07067/home/37008427",
      "source": "Redfin",
      "basement_label": "✅ Basement",
      "garage_label": "🚗 Unknown",
      "property_road": "🏘️ Residential Street (Outlook Avenue)",
      "busy_road": true,
      "near_highway": true,
      "highway_roads": [
        {
          "name": "1234-1210 NJ-27",
          "distance_miles": 0.2
        }
      ],
      "status": "new",
      "first_seen": "2026-07-16"
    },
    "redfin_37791310": {
      "id": "redfin_37791310",
      "address": "29 Rutgers Rd Clark NJ 07066",
      "price": "735000",
      "beds": 3,
      "baths": 2,
      "lot_sqft": "15085",
      "url": "https://www.redfin.com/NJ/Clark/29-Rutgers-Rd-07066/home/37791310",
      "source": "Redfin",
      "basement_label": "✅ Basement",
      "garage_label": "🚗 Unknown",
      "property_road": "🏘️ Residential Street (Rutgers Road)",
      "busy_road": false,
      "near_highway": false,
      "highway_roads": [],
      "status": "new",
      "first_seen": "2026-07-16"
    },
    "redfin_36811262": {
      "id": "redfin_36811262",
      "address": "42 Walnut St Edison NJ 08817",
      "price": "575000",
      "beds": 3,
      "baths": 2,
      "lot_sqft": "9600",
      "url": "https://www.redfin.com/NJ/Edison/42-Walnut-St-08817/home/36811262",
      "source": "Redfin",
      "basement_label": "✅ Basement",
      "garage_label": "🚗 Unknown",
      "property_road": "🏘️ Residential Street (Walnut Street)",
      "busy_road": true,
      "near_highway": true,
      "highway_roads": [
        {
          "name": "1914-1916 NJ-27",
          "distance_miles": 0.25
        }
      ],
      "status": "new",
      "first_seen": "2026-07-16"
    },
    "redfin_37802023": {
      "id": "redfin_37802023",
      "address": "4 Park Ln Princeton NJ 08540",
      "price": "595000",
      "beds": 3,
      "baths": 2,
      "lot_sqft": "38925",
      "url": "https://www.redfin.com/NJ/Princeton/4-Park-Ln-08540/home/37802023",
      "source": "Redfin",
      "basement_label": "✅ Basement",
      "garage_label": "🚗 Unknown",
      "property_road": "🏘️ Residential Street (Park Lane)",
      "busy_road": false,
      "near_highway": false,
      "highway_roads": [],
      "status": "new",
      "first_seen": "2026-07-16"
    },
    "redfin_36951785": {
      "id": "redfin_36951785",
      "address": "44 Garfield Pl Parlin NJ 08859",
      "price": "509999",
      "beds": 4,
      "baths": 2,
      "lot_sqft": "5001",
      "url": "https://www.redfin.com/NJ/Parlin/44-Garfield-Pl-08859/home/36951785",
      "source": "Redfin",
      "basement_label": "✅ Basement",
      "garage_label": "🚗 Unknown",
      "property_road": "🏘️ Residential Street (Garfield Place)",
      "busy_road": false,
      "near_highway": false,
      "highway_roads": [],
      "status": "new",
      "first_seen": "2026-07-16"
    },
    "redfin_36782444": {
      "id": "redfin_36782444",
      "address": "88 Tall Oaks Dr East Brunswick NJ 08816",
      "price": "800000",
      "beds": 4,
      "baths": 3,
      "lot_sqft": null,
      "url": "https://www.redfin.com/NJ/East-Brunswick/88-Tall-Oaks-Dr-08816/home/36782444",
      "source": "Redfin",
      "basement_label": "✅ Basement",
      "garage_label": "🚗 Unknown",
      "property_road": "🏘️ Residential Street (Tall Oaks Drive)",
      "busy_road": false,
      "near_highway": false,
      "highway_roads": [],
      "status": "new",
      "first_seen": "2026-07-16"
    },
    "redfin_37033450": {
      "id": "redfin_37033450",
      "address": "26 Hamilton Ave Edison NJ 08820",
      "price": "699000",
      "beds": 3,
      "baths": 3,
      "lot_sqft": null,
      "url": "https://www.redfin.com/NJ/Edison/26-Hamilton-Ave-08820/home/37033450",
      "source": "Redfin",
      "basement_label": "✅ Basement",
      "garage_label": "🚗 Unknown",
      "property_road": "🏘️ Residential Street (Hamilton Avenue)",
      "busy_road": true,
      "near_highway": true,
      "highway_roads": [
        {
          "name": "Lincoln Highway",
          "distance_miles": 0.18
        }
      ],
      "status": "new",
      "first_seen": "2026-07-16"
    },
    "redfin_36799700": {
      "id": "redfin_36799700",
      "address": "984 New Dover Rd Edison NJ 08820",
      "price": "775000",
      "beds": 4,
      "baths": 3,
      "lot_sqft": "10319",
      "url": "https://www.redfin.com/NJ/Edison/984-New-Dover-Rd-08820/home/36799700",
      "source": "Redfin",
      "basement_label": "✅ Basement",
      "garage_label": "🚗 Unknown",
      "property_road": "🟡 Minor Through-Road (New Dover Road)",
      "busy_road": false,
      "near_highway": false,
      "highway_roads": [],
      "status": "new",
      "first_seen": "2026-07-16"
    },
    "redfin_36815089": {
      "id": "redfin_36815089",
      "address": "24 Winthrop Rd Edison NJ 08817",
      "price": "839900",
      "beds": 4,
      "baths": 3,
      "lot_sqft": "6599",
      "url": "https://www.redfin.com/NJ/Edison/24-Winthrop-Rd-08817/home/36815089",
      "source": "Redfin",
      "basement_label": "✅ Basement",
      "garage_label": "🚗 Unknown",
      "property_road": "🏘️ Residential Street (Winthrop Road)",
      "busy_road": true,
      "near_highway": true,
      "highway_roads": [
        {
          "name": "1999-1997 NJ-27",
          "distance_miles": 0.08
        }
      ],
      "status": "new",
      "first_seen": "2026-07-16"
    },
    "redfin_37935952": {
      "id": "redfin_37935952",
      "address": "54 Platz Dr Skillman NJ 08558",
      "price": "799000",
      "beds": 3,
      "baths": 2.5,
      "lot_sqft": "66647",
      "url": "https://www.redfin.com/NJ/Skillman/54-Platz-Dr-08558/home/37935952",
      "source": "Redfin",
      "basement_label": "✅ Basement",
      "garage_label": "🚗 Unknown",
      "property_road": "🏘️ Residential Street (Platz Drive)",
      "busy_road": false,
      "near_highway": false,
      "highway_roads": [],
      "status": "new",
      "first_seen": "2026-07-16"
    },
    "redfin_36824472": {
      "id": "redfin_36824472",
      "address": "129 Hampton St Metuchen NJ 08840",
      "price": "699900",
      "beds": 3,
      "baths": 3,
      "lot_sqft": "6273",
      "url": "https://www.redfin.com/NJ/Metuchen/129-Hampton-St-08840/home/36824472",
      "source": "Redfin",
      "basement_label": "✅ Basement",
      "garage_label": "🚗 Unknown",
      "property_road": "🏘️ Residential Street (Hampton Street)",
      "busy_road": false,
      "near_highway": false,
      "highway_roads": [],
      "status": "new",
      "first_seen": "2026-07-16"
    },
    "redfin_37802820": {
      "id": "redfin_37802820",
      "address": "35 SE Nassau St Clark NJ 07066",
      "price": "625000",
      "beds": 3,
      "baths": 2.5,
      "lot_sqft": "8000",
      "url": "https://www.redfin.com/NJ/Clark/35-Nassau-St-07066/home/37802820",
      "source": "Redfin",
      "basement_label": "✅ Basement",
      "garage_label": "🚗 Unknown",
      "property_road": "🏘️ Residential Street (Nassau Street)",
      "busy_road": false,
      "near_highway": false,
      "highway_roads": [],
      "status": "new",
      "first_seen": "2026-07-16"
    },
    "redfin_36781523": {
      "id": "redfin_36781523",
      "address": "3 Packard Rd East Brunswick NJ 08816",
      "price": "739900",
      "beds": 4,
      "baths": 2,
      "lot_sqft": "17150",
      "url": "https://www.redfin.com/NJ/East-Brunswick/3-Packard-Rd-08816/home/36781523",
      "source": "Redfin",
      "basement_label": "✅ Basement",
      "garage_label": "🚗 Unknown",
      "property_road": "🏘️ Residential Street (Packard Road)",
      "busy_road": false,
      "near_highway": false,
      "highway_roads": [],
      "status": "new",
      "first_seen": "2026-07-16"
    },
    "redfin_37063447": {
      "id": "redfin_37063447",
      "address": "80 Elm St Spotswood NJ 08884",
      "price": "505000",
      "beds": 3,
      "baths": 2,
      "lot_sqft": "5001",
      "url": "https://www.redfin.com/NJ/Spotswood/80-Elm-St-08884/home/37063447",
      "source": "Redfin",
      "basement_label": "✅ Basement",
      "garage_label": "🚗 Unknown",
      "property_road": "🏘️ Residential Street (Elm Street)",
      "busy_road": false,
      "near_highway": false,
      "highway_roads": [],
      "status": "new",
      "first_seen": "2026-07-16"
    },
    "redfin_36991608": {
      "id": "redfin_36991608",
      "address": "458 Old Bridge Tpke South River NJ 08882",
      "price": "599000",
      "beds": 5,
      "baths": 3,
      "lot_sqft": "10402",
      "url": "https://www.redfin.com/NJ/South-River/458-Old-Bridge-Tpke-08882/home/36991608",
      "source": "Redfin",
      "basement_label": "✅ Basement",
      "garage_label": "🚗 Unknown",
      "property_road": "🟡 Minor Through-Road (Old Bridge Turnpike)",
      "busy_road": false,
      "near_highway": false,
      "highway_roads": [],
      "status": "new",
      "first_seen": "2026-07-16"
    },
    "redfin_36818356": {
      "id": "redfin_36818356",
      "address": "16 Avenue A Ave Helmetta NJ 08828",
      "price": "519000",
      "beds": 3,
      "baths": 2,
      "lot_sqft": null,
      "url": "https://www.redfin.com/NJ/Helmetta/16-Avenue-A-08828/home/36818356",
      "source": "Redfin",
      "basement_label": "✅ Basement",
      "garage_label": "🚗 Unknown",
      "property_road": "🏘️ Residential Street (North 13th Street)",
      "busy_road": false,
      "near_highway": false,
      "highway_roads": [],
      "status": "new",
      "first_seen": "2026-07-16"
    },
    "redfin_36801040": {
      "id": "redfin_36801040",
      "address": "22 Foley Ave Edison NJ 08820",
      "price": "799000",
      "beds": 4,
      "baths": 2,
      "lot_sqft": "17999",
      "url": "https://www.redfin.com/NJ/Edison/22-Foley-Ave-08820/home/36801040",
      "source": "Redfin",
      "basement_label": "✅ Basement",
      "garage_label": "🚗 Unknown",
      "property_road": "🏘️ Residential Street (Foley Avenue)",
      "busy_road": false,
      "near_highway": false,
      "highway_roads": [],
      "status": "new",
      "first_seen": "2026-07-16"
    },
    "redfin_36986031": {
      "id": "redfin_36986031",
      "address": "3764 Fleet Ave South Plainfield NJ 07080",
      "price": "614900",
      "beds": 4,
      "baths": 2,
      "lot_sqft": null,
      "url": "https://www.redfin.com/NJ/South-Plainfield/3764-Fleet-Ave-07080/home/36986031",
      "source": "Redfin",
      "basement_label": "✅ Basement",
      "garage_label": "🚗 Unknown",
      "property_road": "🏘️ Residential Street (Fleet Avenue)",
      "busy_road": false,
      "near_highway": false,
      "highway_roads": [],
      "status": "new",
      "first_seen": "2026-07-16"
    },
    "redfin_36803233": {
      "id": "redfin_36803233",
      "address": "513 Grove Ave Edison NJ 08820",
      "price": "889000",
      "beds": 3,
      "baths": 2,
      "lot_sqft": "29834",
      "url": "https://www.redfin.com/NJ/Edison/513-Grove-Ave-08820/home/36803233",
      "source": "Redfin",
      "basement_label": "✅ Basement",
      "garage_label": "🚗 Unknown",
      "property_road": "🏘️ Residential Street (Kazcmar Court)",
      "busy_road": false,
      "near_highway": false,
      "highway_roads": [],
      "status": "new",
      "first_seen": "2026-07-16"
    },
    "redfin_36847646": {
      "id": "redfin_36847646",
      "address": "7 Michelle St Monroe Township NJ 08831",
      "price": "799900",
      "beds": 4,
      "baths": 2,
      "lot_sqft": "30000",
      "url": "https://www.redfin.com/NJ/Monroe-Township/7-Michelle-St-08831/home/36847646",
      "source": "Redfin",
      "basement_label": "✅ Basement",
      "garage_label": "🚗 Unknown",
      "property_road": "🏘️ Residential Street (Michelle Street)",
      "busy_road": false,
      "near_highway": false,
      "highway_roads": [],
      "status": "new",
      "first_seen": "2026-07-16"
    },
    "redfin_36859150": {
      "id": "redfin_36859150",
      "address": "1177 Aaron Rd North Brunswick NJ 08902",
      "price": "789900",
      "beds": 3,
      "baths": 2.5,
      "lot_sqft": "14959",
      "url": "https://www.redfin.com/NJ/North-Brunswick/1177-Aaron-Rd-08902/home/36859150",
      "source": "Redfin",
      "busy_road": false,
      "near_highway": false,
      "near_industrial": true,
      "status": "new",
      "first_seen": "2026-07-16"
    },
    "redfin_36993904": {
      "id": "redfin_36993904",
      "address": "3 Newark Ave Spotswood NJ 08884",
      "price": "515000",
      "beds": 3,
      "baths": 2,
      "lot_sqft": "5001",
      "url": "https://www.redfin.com/NJ/Spotswood/3-Newark-Ave-08884/home/36993904",
      "source": "Redfin",
      "basement_label": "✅ Basement",
      "garage_label": "🚗 Unknown",
      "property_road": "🏘️ Residential Street (Newark Avenue)",
      "busy_road": false,
      "near_highway": false,
      "highway_roads": [],
      "status": "new",
      "first_seen": "2026-07-16"
    },
    "zillow_39875147": {
      "id": "zillow_39875147",
      "address": "16 Belmar St Franklin Twp. NJ 08873",
      "price": 634900,
      "beds": 3,
      "baths": 2,
      "lot_sqft": "0.37 acres",
      "url": "https://www.zillow.com/homedetails/39875147_zpid/",
      "source": "Zillow",
      "basement_label": "✅ Unfinished Basement",
      "garage_label": "🚗 2-car garage",
      "property_road": "🏘️ Residential Street (Belmar Street)",
      "busy_road": false,
      "near_highway": false,
      "highway_roads": [],
      "status": "new",
      "first_seen": "2026-07-16"
    },
    "zillow_39872209": {
      "id": "zillow_39872209",
      "address": "1868 Amwell Rd Somerset NJ 08873",
      "price": 649000,
      "beds": 3,
      "baths": 2,
      "lot_sqft": "0.8196 acres",
      "url": "https://www.zillow.com/homedetails/39872209_zpid/",
      "source": "Zillow",
      "basement_label": "✅ Basement",
      "garage_label": "🚗 2-car attached garage",
      "property_road": "🟠 Secondary Road (Amwell Road)",
      "busy_road": false,
      "near_highway": false,
      "highway_roads": [],
      "status": "new",
      "first_seen": "2026-07-16"
    },
    "redfin_56023699": {
      "id": "redfin_56023699",
      "address": "40 Watkins Ave Staten Island NY 10312",
      "price": "799000",
      "beds": 4,
      "baths": 2.5,
      "lot_sqft": "2973",
      "url": "https://www.redfin.com/NY/Staten-Island/40-Watkins-Ave-10312/home/56023699",
      "source": "Redfin",
      "basement_label": "✅ Basement",
      "garage_label": "🚗 Unknown",
      "property_road": "🏘️ Residential Street (Watkins Avenue)",
      "busy_road": true,
      "near_highway": true,
      "highway_roads": [
        {
          "name": "Korean War Veterans Parkway",
          "distance_miles": 0.19
        }
      ],
      "status": "new",
      "first_seen": "2026-07-16"
    },
    "redfin_56138189": {
      "id": "redfin_56138189",
      "address": "290 Beach Rd Staten Island NY 10312",
      "price": "749900",
      "beds": 3,
      "baths": 2,
      "lot_sqft": "3800",
      "url": "https://www.redfin.com/NY/Staten-Island/290-Beach-Rd-10312/home/56138189",
      "source": "Redfin",
      "basement_label": "✅ Basement",
      "garage_label": "🚗 Unknown",
      "property_road": "🏘️ Residential Street (Beach Road)",
      "busy_road": false,
      "near_highway": false,
      "highway_roads": [],
      "status": "new",
      "first_seen": "2026-07-16"
    },
    "redfin_56068062": {
      "id": "redfin_56068062",
      "address": "182 Oakdale St Staten Island NY 10308",
      "price": "869000",
      "beds": 3,
      "baths": 2.5,
      "lot_sqft": "6050",
      "url": "https://www.redfin.com/NY/Staten-Island/182-Oakdale-St-10308/home/56068062",
      "source": "Redfin",
      "basement_label": "✅ Basement",
      "garage_label": "🚗 Unknown",
      "property_road": "🟡 Minor Through-Road (Armstrong Avenue)",
      "busy_road": false,
      "near_highway": false,
      "highway_roads": [],
      "status": "new",
      "first_seen": "2026-07-16"
    },
    "redfin_37021194": {
      "id": "redfin_37021194",
      "address": "41 Blair Rd Port Reading NJ 07064",
      "price": "525000",
      "beds": 3,
      "baths": 2,
      "lot_sqft": "8599",
      "url": "https://www.redfin.com/NJ/Port-Reading/41-Blair-Rd-07064/home/37021194",
      "source": "Redfin",
      "basement_label": "✅ Basement",
      "garage_label": "🚗 Unknown",
      "property_road": "🏘️ Residential Street (Raritan Avenue)",
      "busy_road": true,
      "near_highway": true,
      "highway_roads": [
        {
          "name": "New Jersey Turnpike",
          "distance_miles": 0.07
        }
      ],
      "status": "new",
      "first_seen": "2026-07-16"
    },
    "redfin_36761873": {
      "id": "redfin_36761873",
      "address": "22 Longview Ave Carteret NJ 07008",
      "price": "549000",
      "beds": 2,
      "baths": 2,
      "lot_sqft": "5998",
      "url": "https://www.redfin.com/NJ/Carteret/22-Longview-Ave-07008/home/36761873",
      "source": "Redfin",
      "basement_label": "✅ Basement",
      "garage_label": "🚗 Unknown",
      "property_road": "🏘️ Residential Street (Longview Avenue)",
      "busy_road": false,
      "near_highway": false,
      "highway_roads": [],
      "status": "new",
      "first_seen": "2026-07-16"
    },
    "redfin_56088682": {
      "id": "redfin_56088682",
      "address": "330 Lightner Ave Staten Island NY 10314",
      "price": "998000",
      "beds": 4,
      "baths": 2.25,
      "lot_sqft": "5000",
      "url": "https://www.redfin.com/NY/Staten-Island/330-Lightner-Ave-10314/home/56088682",
      "source": "Redfin",
      "basement_label": "✅ Basement",
      "garage_label": "🚗 Unknown",
      "property_road": "🏘️ Residential Street (Melhorn Road)",
      "busy_road": true,
      "near_highway": true,
      "highway_roads": [
        {
          "name": "Staten Island Expressway",
          "distance_miles": 0.17
        }
      ],
      "status": "new",
      "first_seen": "2026-07-16"
    },
    "redfin_36763672": {
      "id": "redfin_36763672",
      "address": "21 Spruce St Carteret NJ 07008",
      "price": "529000",
      "beds": 3,
      "baths": 2,
      "lot_sqft": "5001",
      "url": "https://www.redfin.com/NJ/Carteret/21-Spruce-St-07008/home/36763672",
      "source": "Redfin",
      "basement_label": "✅ Basement",
      "garage_label": "🚗 Unknown",
      "property_road": "🏘️ Residential Street (Arthur Avenue)",
      "busy_road": false,
      "near_highway": false,
      "highway_roads": [],
      "status": "new",
      "first_seen": "2026-07-16"
    },
    "redfin_56047782": {
      "id": "redfin_56047782",
      "address": "24 Schmidts Ln Staten Island NY 10314",
      "price": "890888",
      "beds": 3,
      "baths": 2,
      "lot_sqft": "3920",
      "url": "https://www.redfin.com/NY/Staten-Island/24-Schmidts-Ln-10314/home/56047782",
      "source": "Redfin",
      "basement_label": "✅ Basement",
      "garage_label": "🚗 Unknown",
      "property_road": "🏘️ Residential Street (Schmidts Lane)",
      "busy_road": true,
      "near_highway": true,
      "highway_roads": [
        {
          "name": "Staten Island Expressway",
          "distance_miles": 0.15
        }
      ],
      "status": "new",
      "first_seen": "2026-07-16"
    },
    "redfin_56077372": {
      "id": "redfin_56077372",
      "address": "407 Stoneham St Staten Island NY 10306",
      "price": "730000",
      "beds": 2,
      "baths": 2,
      "lot_sqft": "4100",
      "url": "https://www.redfin.com/NY/Staten-Island/407-Stoneham-St-10306/home/56077372",
      "source": "Redfin",
      "basement_label": "✅ Basement",
      "garage_label": "🚗 Unknown",
      "property_road": "🏘️ Residential Street (Stoneham Street)",
      "busy_road": false,
      "near_highway": false,
      "highway_roads": [],
      "status": "new",
      "first_seen": "2026-07-16"
    },
    "redfin_56018939": {
      "id": "redfin_56018939",
      "address": "128 Ramble Rd Staten Island NY 10308",
      "price": "899000",
      "beds": 3,
      "baths": 2.25,
      "lot_sqft": "4365",
      "url": "https://www.redfin.com/NY/Staten-Island/128-Ramble-Rd-10308/home/56018939",
      "source": "Redfin",
      "basement_label": "✅ Basement",
      "garage_label": "🚗 Unknown",
      "property_road": "🏘️ Residential Street (Ramble Road)",
      "busy_road": false,
      "near_highway": false,
      "highway_roads": [],
      "status": "new",
      "first_seen": "2026-07-16"
    },
    "redfin_56047195": {
      "id": "redfin_56047195",
      "address": "293 Lightner Ave Staten Island NY 10314",
      "price": "925000",
      "beds": 3,
      "baths": 2.25,
      "lot_sqft": "3920",
      "url": "https://www.redfin.com/NY/Staten-Island/293-Lightner-Ave-10314/home/56047195",
      "source": "Redfin",
      "basement_label": "✅ Basement",
      "garage_label": "🚗 Unknown",
      "property_road": "🏘️ Residential Street (Lightner Avenue)",
      "busy_road": true,
      "near_highway": true,
      "highway_roads": [
        {
          "name": "Staten Island Expressway",
          "distance_miles": 0.15
        }
      ],
      "status": "new",
      "first_seen": "2026-07-16"
    },
    "redfin_56096960": {
      "id": "redfin_56096960",
      "address": "826 Lamont Ave Staten Island NY 10309",
      "price": "774000",
      "beds": 3,
      "baths": 2.25,
      "lot_sqft": "4200",
      "url": "https://www.redfin.com/NY/Staten-Island/826-Lamont-Ave-10309/home/56096960",
      "source": "Redfin",
      "basement_label": "✅ Basement",
      "garage_label": "🚗 Unknown",
      "property_road": "🏘️ Residential Street (Lamont Avenue)",
      "busy_road": false,
      "near_highway": false,
      "highway_roads": [],
      "status": "new",
      "first_seen": "2026-07-16"
    },
    "redfin_37027437": {
      "id": "redfin_37027437",
      "address": "1266 Rahway Ave Avenel NJ 07001",
      "price": "500000",
      "beds": 4,
      "baths": 2,
      "lot_sqft": "4901",
      "url": "https://www.redfin.com/NJ/Avenel/1266-Rahway-Ave-07001/home/37027437",
      "source": "Redfin",
      "basement_label": "✅ Basement",
      "garage_label": "🚗 Unknown",
      "property_road": "🟡 Minor Through-Road (Rahway Avenue)",
      "busy_road": false,
      "near_highway": false,
      "highway_roads": [],
      "status": "new",
      "first_seen": "2026-07-16"
    },
    "redfin_56077496": {
      "id": "redfin_56077496",
      "address": "185 Reno Ave Staten Island NY 10306",
      "price": "848880",
      "beds": 3,
      "baths": 2,
      "lot_sqft": "4000",
      "url": "https://www.redfin.com/NY/Staten-Island/185-Reno-Ave-10306/home/56077496",
      "source": "Redfin",
      "basement_label": "✅ Basement",
      "garage_label": "🚗 Unknown",
      "property_road": "🏘️ Residential Street (Reno Avenue)",
      "busy_road": false,
      "near_highway": false,
      "highway_roads": [],
      "status": "new",
      "first_seen": "2026-07-16"
    },
    "redfin_36764756": {
      "id": "redfin_36764756",
      "address": "21 Monroe Ave Carteret NJ 07008",
      "price": "569000",
      "beds": 3,
      "baths": 2,
      "lot_sqft": "7200",
      "url": "https://www.redfin.com/NJ/Carteret/21-Monroe-Ave-07008/home/36764756",
      "source": "Redfin",
      "basement_label": "✅ Basement",
      "garage_label": "🚗 Unknown",
      "property_road": "🏘️ Residential Street (Monroe Avenue)",
      "busy_road": true,
      "near_highway": true,
      "highway_roads": [
        {
          "name": "New Jersey Turnpike",
          "distance_miles": 0.11
        }
      ],
      "status": "new",
      "first_seen": "2026-07-16"
    },
    "redfin_56090412": {
      "id": "redfin_56090412",
      "address": "114 Tallman St Staten Island NY 10312",
      "price": "975000",
      "beds": 4,
      "baths": 2,
      "lot_sqft": "4000",
      "url": "https://www.redfin.com/NY/Staten-Island/114-Tallman-St-10312/home/56090412",
      "source": "Redfin",
      "basement_label": "✅ Basement",
      "garage_label": "🚗 Unknown",
      "property_road": "🏘️ Residential Street (Tallman Street)",
      "busy_road": false,
      "near_highway": false,
      "highway_roads": [],
      "status": "new",
      "first_seen": "2026-07-16"
    },
    "redfin_36906896": {
      "id": "redfin_36906896",
      "address": "595 Jacques St Perth Amboy NJ 08861",
      "price": "524900",
      "beds": 4,
      "baths": 2,
      "lot_sqft": "5001",
      "url": "https://www.redfin.com/NJ/Perth-Amboy/595-Jacques-St-08861/home/36906896",
      "source": "Redfin",
      "basement_label": "✅ Basement",
      "garage_label": "🚗 Unknown",
      "property_road": "🏘️ Residential Street (Jeffries Street)",
      "busy_road": false,
      "near_highway": false,
      "highway_roads": [],
      "status": "new",
      "first_seen": "2026-07-16"
    },
    "zillow_39979903": {
      "id": "zillow_39979903",
      "address": "2 Princeton Road Cranford Twp. NJ 07016",
      "price": 850000,
      "beds": 3,
      "baths": 3,
      "lot_sqft": "0.3 acres",
      "url": "https://www.zillow.com/homedetails/39979903_zpid/",
      "source": "Zillow",
      "basement_label": "✅ Finished Basement",
      "garage_label": "🚗 2-car attached garage",
      "property_road": "🏘️ Residential Street (Princeton Road)",
      "busy_road": false,
      "near_highway": false,
      "highway_roads": [],
      "status": "new",
      "first_seen": "2026-07-16"
    },
    "redfin_37782394": {
      "id": "redfin_37782394",
      "address": "1120 Cambridge Ln Bridgewater NJ 08807-1215",
      "price": "925000",
      "beds": 4,
      "baths": 3,
      "lot_sqft": "71002",
      "url": "https://www.redfin.com/NJ/Bridgewater/1120-Cambridge-Ln-08807/home/37782394",
      "source": "Redfin",
      "basement_label": "❌ No Basement",
      "garage_label": "🚗 3-car garage (Built-In Garage, Detached Garage, Loft Storage)",
      "property_road": "🏘️ Residential Street (Cambridge Lane)",
      "busy_road": false,
      "near_highway": false,
      "highway_roads": [],
      "status": "new",
      "first_seen": "2026-07-17",
      "run_date": "2026-07-17"
    },
    "redfin_37867883": {
      "id": "redfin_37867883",
      "address": "65 Wilson Rd Somerset NJ 08873",
      "price": "595000",
      "beds": 3,
      "baths": 2,
      "lot_sqft": "15050",
      "url": "https://www.redfin.com/NJ/Somerset/65-Wilson-Rd-08873/home/37867883",
      "source": "Redfin",
      "basement_label": "✅ Basement",
      "garage_label": "🚗 Unknown",
      "property_road": "🏘️ Residential Street (Wilson Road)",
      "busy_road": false,
      "near_highway": false,
      "highway_roads": [],
      "status": "new",
      "first_seen": "2026-07-17",
      "run_date": "2026-07-17"
    },
    "redfin_37975796": {
      "id": "redfin_37975796",
      "address": "9 Riviera Dr Somerville NJ 08876-1723",
      "price": "547777",
      "beds": 3,
      "baths": 2,
      "lot_sqft": "7405",
      "url": "https://www.redfin.com/NJ/Somerville/9-Riviera-Dr-08876/home/37975796",
      "source": "Redfin",
      "basement_label": "❌ No Basement",
      "garage_label": "🚗 1-car garage (Attached Garage)",
      "property_road": "🏘️ Residential Street (Riviera Drive)",
      "busy_road": false,
      "near_highway": false,
      "highway_roads": [],
      "status": "new",
      "first_seen": "2026-07-17",
      "run_date": "2026-07-17"
    },
    "redfin_37303330": {
      "id": "redfin_37303330",
      "address": "151 Cottage Pl W Gillette NJ 07933",
      "price": "996000",
      "beds": 5,
      "baths": 3.5,
      "lot_sqft": "13068",
      "url": "https://www.redfin.com/NJ/Gillette/151-Cottage-Pl-W-07933/home/37303330",
      "source": "Redfin",
      "basement_label": "❌ No Basement",
      "garage_label": "🚗 2-car garage (Attached Garage)",
      "property_road": "🏘️ Residential Street (Cottage Place West)",
      "busy_road": false,
      "near_highway": false,
      "highway_roads": [],
      "status": "new",
      "first_seen": "2026-07-17",
      "run_date": "2026-07-17"
    },
    "redfin_37300109": {
      "id": "redfin_37300109",
      "address": "121 Rolling Hill Dr Millington NJ 07946-1207",
      "price": "940000",
      "beds": 5,
      "baths": 4.5,
      "lot_sqft": "30056",
      "url": "https://www.redfin.com/NJ/Millington/121-Rolling-Hill-Dr-07946/home/37300109",
      "source": "Redfin",
      "basement_label": "❌ No Basement",
      "garage_label": "🚗 3-car garage (Attached Garage, Detached Garage, See Remarks)",
      "property_road": "🏘️ Residential Street (Rolling Hill Drive)",
      "busy_road": true,
      "near_highway": true,
      "highway_roads": [
        {
          "name": "1984-1994 County Rte 512",
          "distance_miles": 0.17
        }
      ],
      "status": "new",
      "first_seen": "2026-07-17",
      "run_date": "2026-07-17"
    },
    "redfin_37736920": {
      "id": "redfin_37736920",
      "address": "216 Glen Crest Dr Branchburg NJ 08853-4242",
      "price": "775000",
      "beds": 4,
      "baths": 3,
      "lot_sqft": "85377",
      "url": "https://www.redfin.com/NJ/Branchburg/216-Glen-Crest-Dr-08853/home/37736920",
      "source": "Redfin",
      "basement_label": "❌ No Basement",
      "garage_label": "🚗 2-car garage (Detached Garage, Garage Door Opener, Loft Storage, Oversize Garage)",
      "property_road": "🏘️ Residential Street (Branch Drive)",
      "busy_road": true,
      "near_highway": true,
      "highway_roads": [
        {
          "name": "1314-1346 US-202",
          "distance_miles": 0.33
        }
      ],
      "status": "new",
      "first_seen": "2026-07-17",
      "run_date": "2026-07-17"
    },
    "redfin_37643264": {
      "id": "redfin_37643264",
      "address": "30 Benjamin St Somerset NJ 08873-7260",
      "price": "674000",
      "beds": 2,
      "baths": 2,
      "lot_sqft": "6098",
      "url": "https://www.redfin.com/NJ/Somerset/30-Benjamin-St-08873/home/37643264",
      "source": "Redfin",
      "basement_label": "❌ No Basement",
      "garage_label": "🚗 2-car garage (Attached Garage)",
      "property_road": "🏘️ Residential Street (Benjamin Street)",
      "busy_road": false,
      "near_highway": false,
      "highway_roads": [],
      "status": "new",
      "first_seen": "2026-07-17",
      "run_date": "2026-07-17"
    },
    "redfin_37301336": {
      "id": "redfin_37301336",
      "address": "167 Division Ave Millington NJ 07946-1318",
      "price": "625000",
      "beds": 3,
      "baths": 2,
      "lot_sqft": "34412",
      "url": "https://www.redfin.com/NJ/Millington/167-Division-Ave-07946/home/37301336",
      "source": "Redfin",
      "basement_label": "❌ No Basement",
      "garage_label": "🚗 1-car garage (Attached Garage)",
      "property_road": "🟡 Minor Through-Road (Division Avenue)",
      "busy_road": true,
      "near_highway": true,
      "highway_roads": [
        {
          "name": "1928-1932 County Rte 512",
          "distance_miles": 0.22
        }
      ],
      "status": "new",
      "first_seen": "2026-07-17",
      "run_date": "2026-07-17"
    },
    "redfin_37786217": {
      "id": "redfin_37786217",
      "address": "1280 Oxford Rd Bridgewater NJ 08807-1424",
      "price": "749999",
      "beds": 3,
      "baths": 2,
      "lot_sqft": "32234",
      "url": "https://www.redfin.com/NJ/Bridgewater/1280-Oxford-Rd-08807/home/37786217",
      "source": "Redfin",
      "basement_label": "❌ No Basement",
      "garage_label": "🚗 2-car garage (Attached Garage, Finished Garage)",
      "property_road": "🏘️ Residential Street (Oxford Road)",
      "busy_road": false,
      "near_highway": false,
      "highway_roads": [],
      "status": "new",
      "first_seen": "2026-07-17",
      "run_date": "2026-07-17"
    },
    "redfin_37650835": {
      "id": "redfin_37650835",
      "address": "79 Renaissance Blvd Somerset NJ 08873-6043",
      "price": "625000",
      "beds": 2,
      "baths": 2,
      "lot_sqft": "6098",
      "url": "https://www.redfin.com/NJ/Somerset/79-Renaissance-Blvd-08873/home/37650835",
      "source": "Redfin",
      "basement_label": "❌ No Basement",
      "garage_label": "🚗 2-car garage (Attached Garage)",
      "property_road": "🏘️ Residential Street (Renaissance Boulevard)",
      "busy_road": false,
      "near_highway": false,
      "highway_roads": [],
      "status": "new",
      "first_seen": "2026-07-17",
      "run_date": "2026-07-17"
    },
    "redfin_37915443": {
      "id": "redfin_37915443",
      "address": "1238 Millstone River Rd Hillsborough NJ 08844-4729",
      "price": "695000",
      "beds": 3,
      "baths": 2,
      "lot_sqft": "24393",
      "url": "https://www.redfin.com/NJ/Hillsborough/1238-Millstone-River-Rd-08844/home/37915443",
      "source": "Redfin",
      "basement_label": "❌ No Basement",
      "garage_label": "🚗 2-car garage (Attached Garage)",
      "property_road": "🟠 Secondary Road (Millstone River Road)",
      "busy_road": false,
      "near_highway": false,
      "highway_roads": [],
      "status": "new",
      "first_seen": "2026-07-17",
      "run_date": "2026-07-17"
    },
    "redfin_38026658": {
      "id": "redfin_38026658",
      "address": "263 N Jackson Ave North Plainfield NJ 07060-4332",
      "price": "450000",
      "beds": 3,
      "baths": 2,
      "lot_sqft": "11325",
      "url": "https://www.redfin.com/NJ/North-Plainfield/263-N-Jackson-Ave-07060/home/38026658",
      "source": "Redfin",
      "basement_label": "❌ No Basement",
      "garage_label": "🚗 1-car garage (Attached Garage)",
      "property_road": "🏘️ Residential Street (North Jackson Avenue)",
      "busy_road": false,
      "near_highway": false,
      "highway_roads": [],
      "status": "new",
      "first_seen": "2026-07-17",
      "run_date": "2026-07-17"
    },
    "redfin_38021441": {
      "id": "redfin_38021441",
      "address": "120 Coddington Ave Somerset NJ 08873",
      "price": "829000",
      "beds": 4,
      "baths": 3.5,
      "lot_sqft": "17851",
      "url": "https://www.redfin.com/NJ/Somerset/120-Coddington-Ave-08873/home/38021441",
      "source": "Redfin",
      "basement_label": "✅ Basement",
      "garage_label": "🚗 Unknown",
      "property_road": "🏘️ Residential Street (Codington Avenue)",
      "busy_road": true,
      "near_highway": true,
      "highway_roads": [
        {
          "name": "596-562 US-22",
          "distance_miles": 0.07
        }
      ],
      "status": "new",
      "first_seen": "2026-07-17",
      "run_date": "2026-07-17"
    },
    "redfin_37921743": {
      "id": "redfin_37921743",
      "address": "4 N 16Th Ave Manville NJ 08835-1524",
      "price": "425000",
      "beds": 4,
      "baths": 2,
      "lot_sqft": "6098",
      "url": "https://www.redfin.com/NJ/Manville/4-N-16th-Ave-08835/home/37921743",
      "source": "Redfin",
      "basement_label": "❌ No Basement",
      "garage_label": "🚗 Unknown",
      "property_road": "🏘️ Residential Street (North 16th Avenue)",
      "busy_road": false,
      "near_highway": false,
      "highway_roads": [],
      "status": "new",
      "first_seen": "2026-07-17",
      "run_date": "2026-07-17"
    },
    "redfin_37690280": {
      "id": "redfin_37690280",
      "address": "34 Cross Rd Basking Ridge NJ 07920-1501",
      "price": "850000",
      "beds": 3,
      "baths": 3,
      "lot_sqft": "23958",
      "url": "https://www.redfin.com/NJ/Basking-Ridge/34-Cross-Rd-07920/home/37690280",
      "source": "Redfin",
      "basement_label": "❌ No Basement",
      "garage_label": "🚗 2-car garage (Built-In Garage, Oversize Garage)",
      "property_road": "🟡 Minor Through-Road (Cross Road)",
      "busy_road": false,
      "near_highway": false,
      "highway_roads": [],
      "status": "new",
      "first_seen": "2026-07-17",
      "run_date": "2026-07-17"
    },
    "redfin_37911160": {
      "id": "redfin_37911160",
      "address": "67 Wertsville Rd Hillsborough NJ 08844-3231",
      "price": "875000",
      "beds": 3,
      "baths": 2,
      "lot_sqft": "216928",
      "url": "https://www.redfin.com/NJ/Hillsborough/67-Wertsville-Rd-08844/home/37911160",
      "source": "Redfin",
      "basement_label": "❌ No Basement",
      "garage_label": "🚗 2-car garage (Attached Garage, Garage Door Opener)",
      "property_road": "🟡 Minor Through-Road (Wertsville Road)",
      "busy_road": false,
      "near_highway": false,
      "highway_roads": [],
      "status": "new",
      "first_seen": "2026-07-17",
      "run_date": "2026-07-17"
    },
    "redfin_37643258": {
      "id": "redfin_37643258",
      "address": "32 Benjamin St Somerset NJ 08873-7260",
      "price": "649900",
      "beds": 2,
      "baths": 2,
      "lot_sqft": "6098",
      "url": "https://www.redfin.com/NJ/Somerset/32-Benjamin-St-08873/home/37643258",
      "source": "Redfin",
      "basement_label": "❌ No Basement",
      "garage_label": "🚗 2-car garage (Attached Garage, Garage Door Opener)",
      "property_road": "🏘️ Residential Street (Benjamin Street)",
      "busy_road": false,
      "near_highway": false,
      "highway_roads": [],
      "status": "new",
      "first_seen": "2026-07-17",
      "run_date": "2026-07-17"
    },
    "redfin_36573083": {
      "id": "redfin_36573083",
      "address": "417 Mountain Rd Lebanon NJ 08833-5032",
      "price": "875900",
      "beds": 3,
      "baths": 3,
      "lot_sqft": "121096",
      "url": "https://www.redfin.com/NJ/Lebanon/417-Mountain-Rd-08833/home/36573083",
      "source": "Redfin",
      "basement_label": "❌ No Basement",
      "garage_label": "🚗 2-car garage (Attached Garage)",
      "property_road": "🏘️ Residential Street (Mountain Road)",
      "busy_road": false,
      "near_highway": false,
      "highway_roads": [],
      "status": "new",
      "first_seen": "2026-07-17",
      "run_date": "2026-07-17"
    },
    "redfin_37992009": {
      "id": "redfin_37992009",
      "address": "43 KING GEORGE Rd Warren NJ 07059-7026",
      "price": "735000",
      "beds": 3,
      "baths": 2,
      "lot_sqft": "87555",
      "url": "https://www.redfin.com/NJ/Warren/43-King-George-Rd-07059/home/37992009",
      "source": "Redfin",
      "basement_label": "❌ No Basement",
      "garage_label": "🚗 2-car garage (Attached Garage, Garage Door Opener, Oversize Garage)",
      "property_road": "🏘️ Residential Street (King George Road)",
      "busy_road": false,
      "near_highway": false,
      "highway_roads": [],
      "status": "new",
      "first_seen": "2026-07-17",
      "run_date": "2026-07-17"
    },
    "redfin_37849962": {
      "id": "redfin_37849962",
      "address": "16 Belmar St Somerset NJ 08873-3006",
      "price": "634900",
      "beds": 3,
      "baths": 2,
      "lot_sqft": "16117",
      "url": "https://www.redfin.com/NJ/Somerset/16-Belmar-St-08873/home/37849962",
      "source": "Redfin",
      "basement_label": "❌ No Basement",
      "garage_label": "🚗 2-car garage (Attached Garage)",
      "property_road": "🏘️ Residential Street (Belmar Street)",
      "busy_road": false,
      "near_highway": false,
      "highway_roads": [],
      "status": "new",
      "first_seen": "2026-07-17",
      "run_date": "2026-07-17"
    },
    "redfin_37790185": {
      "id": "redfin_37790185",
      "address": "1825 Kennesaw Way Bridgewater NJ 08807-2315",
      "price": "800000",
      "beds": 4,
      "baths": 2,
      "lot_sqft": "68824",
      "url": "https://www.redfin.com/NJ/Bridgewater/1825-Kennesaw-Way-08807/home/37790185",
      "source": "Redfin",
      "basement_label": "❌ No Basement",
      "garage_label": "🚗 2-car garage (Detached Garage)",
      "property_road": "🏘️ Residential Street (Kennesaw Way)",
      "busy_road": false,
      "near_highway": false,
      "highway_roads": [],
      "status": "new",
      "first_seen": "2026-07-17",
      "run_date": "2026-07-17"
    },
    "redfin_37042899": {
      "id": "redfin_37042899",
      "address": "5 Forest Park Ter Monroe Township NJ 08831",
      "price": "549900",
      "beds": 3,
      "baths": 2,
      "lot_sqft": "9670",
      "url": "https://www.redfin.com/NJ/Monroe-Township/5-Forest-Park-Ter-08831/home/37042899",
      "source": "Redfin",
      "basement_label": "✅ Basement",
      "garage_label": "🚗 Unknown",
      "property_road": "🏘️ Residential Street (Forest Park Terrace)",
      "busy_road": false,
      "near_highway": false,
      "highway_roads": [],
      "status": "new",
      "first_seen": "2026-07-17",
      "run_date": "2026-07-17"
    },
    "redfin_36775101": {
      "id": "redfin_36775101",
      "address": "6 New Dover Rd East Brunswick NJ 08816",
      "price": "799000",
      "beds": 3,
      "baths": 2.5,
      "lot_sqft": "16000",
      "url": "https://www.redfin.com/NJ/East-Brunswick/6-New-Dover-Rd-08816/home/36775101",
      "source": "Redfin",
      "basement_label": "✅ Basement",
      "garage_label": "🚗 Unknown",
      "property_road": "🏘️ Residential Street (New Dover Road)",
      "busy_road": false,
      "near_highway": false,
      "highway_roads": [],
      "status": "new",
      "first_seen": "2026-07-17",
      "run_date": "2026-07-17"
    },
    "redfin_202636607": {
      "id": "redfin_202636607",
      "address": "3 Forest Park Ter #3 Monroe Township NJ 08831-8542",
      "price": "550000",
      "beds": 3,
      "baths": 2,
      "lot_sqft": "8276",
      "url": "https://www.redfin.com/NJ/Monroe-Township/3-Forest-Park-Ter-08831/unit-3/home/202636607",
      "source": "Redfin",
      "basement_label": "❌ No Basement",
      "garage_label": "🚗 Unknown",
      "property_road": "🏘️ Residential Street (Forest Park Terrace)",
      "busy_road": false,
      "near_highway": false,
      "highway_roads": [],
      "status": "new",
      "first_seen": "2026-07-17",
      "run_date": "2026-07-17"
    },
    "redfin_37994827": {
      "id": "redfin_37994827",
      "address": "1425 Prospect Ave Plainfield NJ 07060-3134",
      "price": "699900",
      "beds": 4,
      "baths": 3.5,
      "lot_sqft": "13068",
      "url": "https://www.redfin.com/NJ/Plainfield/1425-Prospect-Ave-07060/home/37994827",
      "source": "Redfin",
      "basement_label": "❌ No Basement",
      "garage_label": "🚗 2-car garage (Built-In Garage)",
      "property_road": "🏘️ Residential Street (Prospect Avenue)",
      "busy_road": false,
      "near_highway": false,
      "highway_roads": [],
      "status": "new",
      "first_seen": "2026-07-17",
      "run_date": "2026-07-17"
    },
    "redfin_36848576": {
      "id": "redfin_36848576",
      "address": "3 Forest Park Ter Monroe Township NJ 08831",
      "price": "550000",
      "beds": 3,
      "baths": 2,
      "lot_sqft": "8455",
      "url": "https://www.redfin.com/NJ/Monroe-Township/3-Forest-Park-Ter-08831/home/36848576",
      "source": "Redfin",
      "basement_label": "❌ No Basement",
      "garage_label": "🚗 Unknown",
      "property_road": "🏘️ Residential Street (Forest Park Terrace)",
      "busy_road": false,
      "near_highway": false,
      "highway_roads": [],
      "status": "new",
      "first_seen": "2026-07-17",
      "run_date": "2026-07-17"
    },
    "redfin_37797540": {
      "id": "redfin_37797540",
      "address": "12 Whitley Ter Clark NJ 07066-2317",
      "price": "785000",
      "beds": 3,
      "baths": 2.5,
      "lot_sqft": "9147",
      "url": "https://www.redfin.com/NJ/Clark/12-Whitley-Ter-07066/home/37797540",
      "source": "Redfin",
      "basement_label": "❌ No Basement",
      "garage_label": "🚗 1-car garage (Attached Garage)",
      "property_road": "🏘️ Residential Street (Whitley Terrace)",
      "busy_road": true,
      "near_highway": true,
      "highway_roads": [
        {
          "name": "Garden State Parkway",
          "distance_miles": 0.08
        }
      ],
      "status": "new",
      "first_seen": "2026-07-17",
      "run_date": "2026-07-17"
    },
    "redfin_36976643": {
      "id": "redfin_36976643",
      "address": "21 Tyndall Rd Kendall Park NJ 08824",
      "price": "674900",
      "beds": 3,
      "baths": 2,
      "lot_sqft": "17550",
      "url": "https://www.redfin.com/NJ/Kendall-Park/21-Tyndall-Rd-08824/home/36976643",
      "source": "Redfin",
      "basement_label": "❌ No Basement",
      "garage_label": "🚗 Unknown",
      "property_road": "🏘️ Residential Street (Tyndall Road)",
      "busy_road": false,
      "near_highway": false,
      "highway_roads": [],
      "status": "new",
      "first_seen": "2026-07-17",
      "run_date": "2026-07-17"
    },
    "redfin_169559773": {
      "id": "redfin_169559773",
      "address": "44 Park Gate Dr Dr #44 Edison NJ 08820",
      "price": "579900",
      "beds": 2,
      "baths": 2,
      "lot_sqft": null,
      "url": "https://www.redfin.com/NJ/Edison/44-Park-Gate-Dr-08820/unit-44/home/169559773",
      "source": "Redfin",
      "basement_label": "❌ No Basement",
      "garage_label": "🚗 Unknown",
      "property_road": "",
      "busy_road": false,
      "near_highway": false,
      "highway_roads": [],
      "status": "new",
      "first_seen": "2026-07-17",
      "run_date": "2026-07-17"
    },
    "redfin_37791265": {
      "id": "redfin_37791265",
      "address": "77 Schwinn Dr Clark NJ 07066-2724",
      "price": "888888",
      "beds": 4,
      "baths": 3,
      "lot_sqft": "16117",
      "url": "https://www.redfin.com/NJ/Clark/77-Schwinn-Dr-07066/home/37791265",
      "source": "Redfin",
      "basement_label": "❌ No Basement",
      "garage_label": "🚗 1-car garage (Attached Garage)",
      "property_road": "🏘️ Residential Street (Schwinn Drive)",
      "busy_road": false,
      "near_highway": false,
      "highway_roads": [],
      "status": "new",
      "first_seen": "2026-07-17",
      "run_date": "2026-07-17"
    },
    "redfin_37791258": {
      "id": "redfin_37791258",
      "address": "17 Schwinn Dr Clark NJ 07066-2724",
      "price": "824500",
      "beds": 3,
      "baths": 3,
      "lot_sqft": "14810",
      "url": "https://www.redfin.com/NJ/Clark/17-Schwinn-Dr-07066/home/37791258",
      "source": "Redfin",
      "basement_label": "❌ No Basement",
      "garage_label": "🚗 1-car garage (Attached Garage)",
      "property_road": "🏘️ Residential Street (Schwinn Drive)",
      "busy_road": false,
      "near_highway": false,
      "highway_roads": [],
      "status": "new",
      "first_seen": "2026-07-17",
      "run_date": "2026-07-17"
    },
    "redfin_169559665": {
      "id": "redfin_169559665",
      "address": "2 Park Gate Dr #1002 Edison NJ 08820",
      "price": "650000",
      "beds": 2,
      "baths": 2,
      "lot_sqft": "39",
      "url": "https://www.redfin.com/NJ/Edison/2-Park-Gate-Dr-08820/unit-1002/home/169559665",
      "source": "Redfin",
      "basement_label": "❌ No Basement",
      "garage_label": "🚗 Unknown",
      "property_road": "",
      "busy_road": false,
      "near_highway": false,
      "highway_roads": [],
      "status": "new",
      "first_seen": "2026-07-17",
      "run_date": "2026-07-17"
    },
    "redfin_36706759": {
      "id": "redfin_36706759",
      "address": "6 Holly Manor Ct Helmetta NJ 08828",
      "price": "479999",
      "beds": 2,
      "baths": 2,
      "lot_sqft": "6970",
      "url": "https://www.redfin.com/NJ/Helmetta/6-Holly-Manor-Ct-08828/home/36706759",
      "source": "Redfin",
      "basement_label": "❌ No Basement",
      "garage_label": "🚗 Unknown",
      "property_road": "🏘️ Residential Street (Holly Manor Court)",
      "busy_road": false,
      "near_highway": false,
      "highway_roads": [],
      "status": "new",
      "first_seen": "2026-07-17",
      "run_date": "2026-07-17"
    },
    "redfin_36814585": {
      "id": "redfin_36814585",
      "address": "15 Markham Rd Edison NJ 08817",
      "price": "679000",
      "beds": 4,
      "baths": 2,
      "lot_sqft": "8364",
      "url": "https://www.redfin.com/NJ/Edison/15-Markham-Rd-08817/home/36814585",
      "source": "Redfin",
      "basement_label": "❌ No Basement",
      "garage_label": "🚗 Unknown",
      "property_road": "🏘️ Residential Street (Markham Road)",
      "busy_road": false,
      "near_highway": false,
      "highway_roads": [],
      "status": "new",
      "first_seen": "2026-07-17",
      "run_date": "2026-07-17"
    },
    "redfin_36730721": {
      "id": "redfin_36730721",
      "address": "107 Monmouth Rd Monroe Township NJ 08831",
      "price": "730000",
      "beds": 4,
      "baths": 2,
      "lot_sqft": null,
      "url": "https://www.redfin.com/NJ/Monroe-Township/107-Monmouth-Rd-08831/home/36730721",
      "source": "Redfin",
      "basement_label": "❌ No Basement",
      "garage_label": "🚗 Unknown",
      "property_road": "🏘️ Residential Street (Monmouth Road)",
      "busy_road": false,
      "near_highway": false,
      "highway_roads": [],
      "status": "new",
      "first_seen": "2026-07-17",
      "run_date": "2026-07-17"
    },
    "redfin_36770393": {
      "id": "redfin_36770393",
      "address": "188 W Wycoff Way East Brunswick NJ 08816",
      "price": "349500",
      "beds": 2,
      "baths": 2,
      "lot_sqft": "4792",
      "url": "https://www.redfin.com/NJ/East-Brunswick/188-Wycoff-Way-W-08816/home/36770393",
      "source": "Redfin",
      "basement_label": "❌ No Basement",
      "garage_label": "🚗 Unknown",
      "property_road": "🏘️ Residential Street (Wycoff Way West)",
      "busy_road": false,
      "near_highway": false,
      "highway_roads": [],
      "status": "new",
      "first_seen": "2026-07-17",
      "run_date": "2026-07-17"
    },
    "zillow_121883626": {
      "id": "zillow_121883626",
      "address": "90 Schindler Ct Franklin Twp. NJ 08873",
      "price": 899000,
      "beds": 3,
      "baths": 3,
      "lot_sqft": 7405.2,
      "url": "https://www.zillow.com/homedetails/121883626_zpid/",
      "source": "Zillow",
      "basement_label": "❌ No Basement",
      "garage_label": "🚗 2-car garage",
      "property_road": "🏘️ Residential Street (Schindler Court)",
      "busy_road": false,
      "near_highway": false,
      "highway_roads": [],
      "status": "new",
      "first_seen": "2026-07-17",
      "run_date": "2026-07-17"
    },
    "zillow_104354624": {
      "id": "zillow_104354624",
      "address": "47 Schindler Ct Franklin Twp. NJ 08873",
      "price": 925000,
      "beds": 3,
      "baths": 4,
      "lot_sqft": 6098.4,
      "url": "https://www.zillow.com/homedetails/104354624_zpid/",
      "source": "Zillow",
      "basement_label": "❌ No Basement",
      "garage_label": "🚗 2-car attached garage",
      "property_road": "🏘️ Residential Street (Schindler Court)",
      "busy_road": false,
      "near_highway": false,
      "highway_roads": [],
      "status": "new",
      "first_seen": "2026-07-17",
      "run_date": "2026-07-17"
    },
    "redfin_38024124": {
      "id": "redfin_38024124",
      "address": "615 Spruce St Roselle NJ 07203-2131",
      "price": "475000",
      "beds": 3,
      "baths": 2,
      "lot_sqft": "3484",
      "url": "https://www.redfin.com/NJ/Roselle/615-Spruce-St-07203/home/38024124",
      "source": "Redfin",
      "basement_label": "❌ No Basement",
      "garage_label": "🚗 Unknown",
      "property_road": "🏘️ Residential Street (Spruce Street)",
      "busy_road": false,
      "near_highway": false,
      "highway_roads": [],
      "status": "new",
      "first_seen": "2026-07-17",
      "run_date": "2026-07-17"
    },
    "redfin_37068040": {
      "id": "redfin_37068040",
      "address": "125 W Minna Ave Avenel NJ 07001",
      "price": "579000",
      "beds": 3,
      "baths": 2,
      "lot_sqft": "10724",
      "url": "https://www.redfin.com/NJ/Avenel/125-Minna-Ave-07001/home/37068040",
      "source": "Redfin",
      "basement_label": "✅ Basement",
      "garage_label": "🚗 Unknown",
      "property_road": "🏘️ Residential Street (Minna Avenue)",
      "busy_road": true,
      "near_highway": true,
      "highway_roads": [
        {
          "name": "925-913 US-1",
          "distance_miles": 0.08
        }
      ],
      "status": "new",
      "first_seen": "2026-07-17",
      "run_date": "2026-07-17"
    },
    "redfin_37211439": {
      "id": "redfin_37211439",
      "address": "30 Ferndale Rd Madison NJ 07940-1404",
      "price": "899000",
      "beds": 3,
      "baths": 2,
      "lot_sqft": "11761",
      "url": "https://www.redfin.com/NJ/Madison/30-Ferndale-Rd-07940/home/37211439",
      "source": "Redfin",
      "basement_label": "❌ No Basement",
      "garage_label": "🚗 2-car garage (Detached Garage)",
      "property_road": "🏘️ Residential Street (Ferndale Road)",
      "busy_road": false,
      "near_highway": false,
      "highway_roads": [],
      "status": "new",
      "first_seen": "2026-07-17",
      "run_date": "2026-07-17"
    },
    "redfin_38077415": {
      "id": "redfin_38077415",
      "address": "28 Warwick Cir Springfield NJ 07081-2244",
      "price": "699999",
      "beds": 3,
      "baths": 3,
      "lot_sqft": "7405",
      "url": "https://www.redfin.com/NJ/Springfield/28-Warwick-Cir-07081/home/38077415",
      "source": "Redfin",
      "basement_label": "❌ No Basement",
      "garage_label": "🚗 1-car garage (Attached Garage)",
      "property_road": "🏘️ Residential Street (Warwick Circle)",
      "busy_road": false,
      "near_highway": false,
      "highway_roads": [],
      "status": "new",
      "first_seen": "2026-07-17",
      "run_date": "2026-07-17"
    },
    "redfin_37810489": {
      "id": "redfin_37810489",
      "address": "2 Princeton Rd Cranford NJ 07016-1520",
      "price": "850000",
      "beds": 3,
      "baths": 2.5,
      "lot_sqft": "13068",
      "url": "https://www.redfin.com/NJ/Cranford/2-Princeton-Rd-07016/home/37810489",
      "source": "Redfin",
      "basement_label": "❌ No Basement",
      "garage_label": "🚗 2-car garage (Built-In Garage, Garage Door Opener, Garage Under, Oversize Garage, See Remarks)",
      "property_road": "🏘️ Residential Street (Princeton Road)",
      "busy_road": false,
      "near_highway": false,
      "highway_roads": [],
      "status": "new",
      "first_seen": "2026-07-17",
      "run_date": "2026-07-17"
    },
    "redfin_37999638": {
      "id": "redfin_37999638",
      "address": "328 W Inman Ave Rahway NJ 07065-2835",
      "price": "550000",
      "beds": 3,
      "baths": 2,
      "lot_sqft": "4356",
      "url": "https://www.redfin.com/NJ/Rahway/328-W-Inman-Ave-07065/home/37999638",
      "source": "Redfin",
      "basement_label": "❌ No Basement",
      "garage_label": "🚗 1-car garage (Built-In Garage)",
      "property_road": "🟠 Secondary Road (West Inman Avenue)",
      "busy_road": false,
      "near_highway": false,
      "highway_roads": [],
      "status": "new",
      "first_seen": "2026-07-17",
      "run_date": "2026-07-17"
    },
    "redfin_37919213": {
      "id": "redfin_37919213",
      "address": "441 N 15Th St Kenilworth NJ 07033-1068",
      "price": "999999",
      "beds": 5,
      "baths": 3,
      "lot_sqft": "6969",
      "url": "https://www.redfin.com/NJ/Kenilworth/441-N-15th-St-07033/home/37919213",
      "source": "Redfin",
      "basement_label": "❌ No Basement",
      "garage_label": "🚗 2-car garage (Attached Garage, Finished Garage, Garage Parking, On-Street Parking, Oversize Garage)",
      "property_road": "🏘️ Residential Street (North 15th Street)",
      "busy_road": false,
      "near_highway": false,
      "highway_roads": [],
      "status": "new",
      "first_seen": "2026-07-17",
      "run_date": "2026-07-17"
    },
    "redfin_37807722": {
      "id": "redfin_37807722",
      "address": "556 Valley Rd Clark NJ 07066-1957",
      "price": "655000",
      "beds": 3,
      "baths": 2.5,
      "lot_sqft": "14374",
      "url": "https://www.redfin.com/NJ/Clark/556-Valley-Rd-07066/home/37807722",
      "source": "Redfin",
      "basement_label": "❌ No Basement",
      "garage_label": "🚗 1-car garage (Built-In Garage)",
      "property_road": "🟡 Minor Through-Road (Valley Road)",
      "busy_road": false,
      "near_highway": false,
      "highway_roads": [],
      "status": "new",
      "first_seen": "2026-07-17",
      "run_date": "2026-07-17"
    },
    "redfin_36184610": {
      "id": "redfin_36184610",
      "address": "2 Millstone Dr Livingston NJ 07039-1810",
      "price": "969000",
      "beds": 4,
      "baths": 2.5,
      "lot_sqft": "14810",
      "url": "https://www.redfin.com/NJ/Livingston/2-Millstone-Dr-07039/home/36184610",
      "source": "Redfin",
      "basement_label": "❌ No Basement",
      "garage_label": "🚗 2-car garage (Built-In Garage, Garage Door Opener, Oversize Garage)",
      "property_road": "🔴 Primary Arterial (West Mount Pleasant Avenue)",
      "busy_road": true,
      "near_highway": true,
      "highway_roads": [
        {
          "name": "272-278 NJ-10",
          "distance_miles": 0.04
        }
      ],
      "status": "new",
      "first_seen": "2026-07-17",
      "run_date": "2026-07-17"
    },
    "redfin_56023697": {
      "id": "redfin_56023697",
      "address": "47 Stanley Cir Staten Island NY 10308",
      "price": "939000",
      "beds": 4,
      "baths": 2.5,
      "lot_sqft": "3800",
      "url": "https://www.redfin.com/NY/Staten-Island/47-Stanley-Cir-10308/home/56023697",
      "source": "Redfin",
      "basement_label": "❌ No Basement",
      "garage_label": "🚗 Unknown",
      "property_road": "🏘️ Residential Street (Stanley Circle)",
      "busy_road": false,
      "near_highway": false,
      "highway_roads": [],
      "status": "new",
      "first_seen": "2026-07-17",
      "run_date": "2026-07-17"
    },
    "redfin_37952922": {
      "id": "redfin_37952922",
      "address": "1399 Birch Hill Rd Mountainside NJ 07092-1831",
      "price": "825000",
      "beds": 3,
      "baths": 2,
      "lot_sqft": "13068",
      "url": "https://www.redfin.com/NJ/Mountainside/1399-Birch-Hill-Rd-07092/home/37952922",
      "source": "Redfin",
      "basement_label": "❌ No Basement",
      "garage_label": "🚗 1-car garage (Attached Garage, Oversize Garage)",
      "property_road": "🏘️ Residential Street (Birch Hill Road)",
      "busy_road": true,
      "near_highway": true,
      "highway_roads": [
        {
          "name": "1412-1422 US-22",
          "distance_miles": 0.11
        }
      ],
      "status": "new",
      "first_seen": "2026-07-17",
      "run_date": "2026-07-17"
    },
    "redfin_37944875": {
      "id": "redfin_37944875",
      "address": "825 Mccandless Pl Linden NJ 07036-1345",
      "price": "500000",
      "beds": 3,
      "baths": 2,
      "lot_sqft": "4356",
      "url": "https://www.redfin.com/NJ/Linden/825-McCandless-Pl-07036/home/37944875",
      "source": "Redfin",
      "basement_label": "❌ No Basement",
      "garage_label": "🚗 Unknown",
      "property_road": "🏘️ Residential Street (McCandless Place)",
      "busy_road": true,
      "near_highway": true,
      "highway_roads": [
        {
          "name": "Interstate 278",
          "distance_miles": 0.17
        }
      ],
      "status": "new",
      "first_seen": "2026-07-17",
      "run_date": "2026-07-17"
    },
    "redfin_36362478": {
      "id": "redfin_36362478",
      "address": "55 Rock Spring Ave West Orange NJ 07052-2626",
      "price": "879000",
      "beds": 4,
      "baths": 3.5,
      "lot_sqft": "27442",
      "url": "https://www.redfin.com/NJ/West-Orange/55-Rock-Spring-Ave-07052/home/36362478",
      "source": "Redfin",
      "basement_label": "❌ No Basement",
      "garage_label": "🚗 2-car garage (Built-In Garage)",
      "property_road": "🏘️ Residential Street (Rock Spring Avenue)",
      "busy_road": false,
      "near_highway": false,
      "highway_roads": [],
      "status": "new",
      "first_seen": "2026-07-17",
      "run_date": "2026-07-17"
    },
    "redfin_36363366": {
      "id": "redfin_36363366",
      "address": "44 Korwel Cir West Orange NJ 07052-1231",
      "price": "725000",
      "beds": 3,
      "baths": 2.5,
      "lot_sqft": "7840",
      "url": "https://www.redfin.com/NJ/West-Orange/44-Korwel-Cir-07052/home/36363366",
      "source": "Redfin",
      "basement_label": "❌ No Basement",
      "garage_label": "🚗 2-car garage (Garage Door Opener, Garage Under)",
      "property_road": "🏘️ Residential Street (Korwel Circle)",
      "busy_road": false,
      "near_highway": false,
      "highway_roads": [],
      "status": "new",
      "first_seen": "2026-07-17",
      "run_date": "2026-07-17"
    },
    "redfin_37950071": {
      "id": "redfin_37950071",
      "address": "486 Summit Rd Mountainside NJ 07092-1524",
      "price": "980000",
      "beds": 3,
      "baths": 3.5,
      "lot_sqft": "14374",
      "url": "https://www.redfin.com/NJ/Mountainside/486-Summit-Rd-07092/home/37950071",
      "source": "Redfin",
      "basement_label": "❌ No Basement",
      "garage_label": "🚗 2-car garage (Built-In Garage, Finished Garage, Garage Door Opener, Oversize Garage)",
      "property_road": "🟠 Secondary Road (Summit Road)",
      "busy_road": false,
      "near_highway": false,
      "highway_roads": [],
      "status": "new",
      "first_seen": "2026-07-17",
      "run_date": "2026-07-17"
    },
    "redfin_56093931": {
      "id": "redfin_56093931",
      "address": "230 Lindenwood Rd Staten Island NY 10308",
      "price": "745000",
      "beds": 4,
      "baths": 2,
      "lot_sqft": "5400",
      "url": "https://www.redfin.com/NY/Staten-Island/230-Lindenwood-Rd-10308/home/56093931",
      "source": "Redfin",
      "basement_label": "❌ No Basement",
      "garage_label": "🚗 Unknown",
      "property_road": "🏘️ Residential Street (Hillcrest Avenue)",
      "busy_road": false,
      "near_highway": false,
      "highway_roads": [],
      "status": "new",
      "first_seen": "2026-07-17",
      "run_date": "2026-07-17"
    },
    "redfin_36761518": {
      "id": "redfin_36761518",
      "address": "383 Carteret Ave Carteret NJ 07008",
      "price": "649999",
      "beds": 3,
      "baths": 3,
      "lot_sqft": null,
      "url": "https://www.redfin.com/NJ/Carteret/383-Carteret-Ave-07008/home/36761518",
      "source": "Redfin",
      "basement_label": "✅ Basement",
      "garage_label": "🚗 Unknown",
      "property_road": "🏘️ Residential Street (Elm Street)",
      "busy_road": true,
      "near_highway": true,
      "highway_roads": [
        {
          "name": "New Jersey Turnpike",
          "distance_miles": 0.14
        }
      ],
      "status": "new",
      "first_seen": "2026-07-17",
      "run_date": "2026-07-17"
    }
  }
}